tuya/__init__.py
tuya/devices.py
tuyasmartapi-0.1.2.dist-info/LICENSE
tuyasmartapi-0.1.2.dist-info/METADATA
tuyasmartapi-0.1.2.dist-info/WHEEL
tuyasmartapi-0.1.2.dist-info/top_level.txt
tuyasmartapi-0.1.2.dist-info/RECORD
