Metadata-Version: 2.1
Name: tuyasmartapi
Version: 0.1.2
Summary: A python client for Tuya Smart devices.
Home-page: https://github.com/shubhamdipt/tuyasmartapi
Author: Shubham Dipt
Author-email: shubham.dipt@gmail.com
License: MIT License
Requires-Dist: certifi (==2019.9.11)
Requires-Dist: chardet (==3.0.4)
Requires-Dist: idna (==2.8)
Requires-Dist: requests (==2.22.0)
Requires-Dist: tuyapy (==0.1.3)
Requires-Dist: urllib3 (==1.25.5)
